<?xml version="1.0" encoding="UTF-8"?>
<tns:patch closeOnSuccess="false" retryOnFail="true"
	xmlns:tns="http://docs.ampdev.net/schemas/xmlpatcher" xmlns:xsi="http://www.w3.org/2001/XMLSchema-instance"
	xsi:schemaLocation="http://docs.ampdev.net/schemas/xmlpatcher ../doc/xmlpatcher.xsd ">
	<jira>AMP-14167</jira>
	<keyword>Views</keyword>
	<author>Alexandru Artimon</author>
	<description>recreate view, this will always be the last version of the view</description>
	<trigger type="all">
		<condition type="custom">
			<script returnVar="val">
				<lang type="sql">
					SELECT settingsvalue FROM amp_global_settings where settingsname='Recreate the views on the next server restart';
				</lang>
			</script>
 			<test>val.equalsIgnoreCase("true")</test>
		</condition>
	</trigger> 
	<apply>
		<script>
			<lang delimiter=";" type="postgres">
				DROP VIEW IF EXISTS v_regions;
				CREATE OR REPLACE VIEW v_regions AS 
			    	SELECT ra.amp_activity_id, regions.region_name AS region, regions.region_id AS region_id, sum(ra.location_percentage) AS location_percentage 
						FROM amp_activity_location ra, amp_location_cache regions
						WHERE (ra.amp_location_id = regions.amp_location_id) AND (regions.region_id IS NOT NULL)
						GROUP BY ra.amp_activity_id, regions.region_id, regions.region_name;
        		</lang>
		</script>
	</apply>
</tns:patch>
