<?xml version="1.0" encoding="UTF-8"?>
<tns:patch closeOnSuccess="true" retryOnFail="true"
	xmlns:tns="http://docs.ampdev.net/schemas/xmlpatcher" xmlns:xsi="http://www.w3.org/2001/XMLSchema-instance"
	xsi:schemaLocation="http://docs.ampdev.net/schemas/xmlpatcher ../doc/xmlpatcher.xsd ">
	<jira>AMP-16005</jira>
	<keyword>Pledges</keyword>
	<author>Ddimunzio</author>
	<description>Have the ability to enter the Agreement / Pledge title as free text instead of using the drop-down that's linked to category manager</description>
	<apply>
		<script>
			<lang delimiter=";" type="postgres">
			</lang>
		</script>
	</apply>
</tns:patch>